README.rst
setup.py
dtoolbioimage/__init__.py
dtoolbioimage/annotation.py
dtoolbioimage/convert.py
dtoolbioimage/derived_dataset.py
dtoolbioimage/ilogging.py
dtoolbioimage/ipyutils.py
dtoolbioimage/region.py
dtoolbioimage/segment.py
dtoolbioimage/transformation.py
dtoolbioimage.egg-info/PKG-INFO
dtoolbioimage.egg-info/SOURCES.txt
dtoolbioimage.egg-info/dependency_links.txt
dtoolbioimage.egg-info/entry_points.txt
dtoolbioimage.egg-info/not-zip-safe
dtoolbioimage.egg-info/requires.txt
dtoolbioimage.egg-info/top_level.txt
dtoolbioimage/util/__init__.py
dtoolbioimage/util/array.py
dtoolbioimage/util/color.py
dtoolbioimage/util/shape.py