Metadata-Version: 1.0
Name: dtoolbioimage
Version: 0.1.12
Summary: dtool bioimaging utilties
Home-page: https://github.com/JIC-Image-Analysis/dtoolbioimage
Author: Matthew Hartley
Author-email: Matthew.Hartley@jic.ac.uk
License: MIT
Platform: UNKNOWN
